Workbook

Sheet LEEME
A1: Archivo | B1: 07_calculadora_escenarios.xlsx · versión 0.1 (mock)
A2: Tipo | B2: ESPECÍFICO: motor de cálculo de la negociación
A3: Qué contiene | B3: Calcula inversión, flujo, recuperación, retorno, margen y zona de acuerdo para tres escenarios. Incluye hojas ref_* con copias de 01, 02, 03, 04 y 06.
A4: Dueño de los cambios | B4: Procedimiento de oferta (el dueño cambia las entradas de cada escenario).
A5: Quién lo lee o consume | B5: Dueño y asesores para preparar propuestas.
A6: Confidencialidad | B6: Contiene costos (ref_equipos). Tratar como interno.
A7: Cómo se usa | B7: Las hojas ref_* deben coincidir con sus archivos fuente. Si difieren, la calculadora está mal aunque las fórmulas sean correctas.
A8: Estado | B8: mock. Las hojas ref_* son copias de referencia: en producción el backend las lee de la base y este archivo ya no las guarda.
A9: Convenciones | B9: Azul = valor editable (supuesto o dato de prueba). Negro = fórmula. Verde = vínculo a otra hoja. Amarillo = supuesto clave.

Sheet escenarios
A1: Escenarios de negociación
A2: Azul = entrada editable. Negro = fórmula. Las referencias apuntan a las hojas ref_*.
A4: Concepto | B4: Propuesta inicial | C4: Contraoferta viable | D4: Sin acuerdo | E4: Nota
A5: Producto (product_id) | B5: ozonette | C5: ozonette | D5: ozonette
A6: Precio por sesión que cobra la clínica (PEN) | B6: 120 | C6: 110 | D6: 90 | E6: Dato del cliente (mock)
A7: Sesiones de ozonoterapia por mes | B7: 40 | C7: 40 | D7: 30 | E7: Dato del cliente (mock)
A8: Precio del equipo (USD) | B8: 6500 | C8: 6100 | D8: 6500 | E8: Palanca de Tecnocare
A9: Instalación incluida (1 = sí, 0 = no) | B9: 0 | C9: 1 | D9: 0 | E9: Palanca de Tecnocare
A10: Capacitación incluida (sesiones) | B10: 2 | C10: 2 | D10: 2 | E10: Palanca de Tecnocare; mínimo en 06 (U-03)
A12: Clínica
A13: Tipo de cambio (PEN por USD) | B13: =ref_parametros!$B$2 -> 3.75 | C13: =ref_parametros!$B$2 -> 3.75 | D13: =ref_parametros!$B$2 -> 3.75 | E13: Vínculo a ref_parametros (04, P-01)
A14: Precio por sesión (USD) | B14: =B6/B13 -> 32 | C14: =C6/C13 -> 29.333333 | D14: =D6/D13 -> 24
A15: Costo de insumos por sesión (USD) | B15: =INDEX(ref_equipos!$D$2:$D$10,MATCH(B$5,ref_equipos!$A$2:$A$10,0)) -> 15 | C15: =INDEX(ref_equipos!$D$2:$D$10,MATCH(C$5,ref_equipos!$A$2:$A$10,0)) -> 15 | D15: =INDEX(ref_equipos!$D$2:$D$10,MATCH(D$5,ref_equipos!$A$2:$A$10,0)) -> 15 | E15: ref_equipos
A16: Flujo neto mensual de la clínica (USD) | B16: =B7*(B14-B15) -> 680 | C16: =C7*(C14-C15) -> 573.33333 | D16: =D7*(D14-D15) -> 270 | E16: Sesiones × (precio − insumo)
A17: Inversión: precio del equipo (USD) | B17: =B8 -> 6500 | C17: =C8 -> 6100 | D17: =D8 -> 6500
A18: Inversión: instalación cobrada (USD) | B18: =IF(B9=1,0,INDEX(ref_equipos!$B$2:$B$10,MATCH(B$5,ref_equipos!$A$2:$A$10,0))) -> 400 | C18: =IF(C9=1,0,INDEX(ref_equipos!$B$2:$B$10,MATCH(C$5,ref_equipos!$A$2:$A$10,0))) -> 0 | D18: =IF(D9=1,0,INDEX(ref_equipos!$B$2:$B$10,MATCH(D$5,ref_equipos!$A$2:$A$10,0))) -> 400 | E18: Cero si la instalación va incluida
A19: Inversión: capacitación cobrada (USD) | B19: =MAX(0,INDEX(ref_equipos!$H$2:$H$10,MATCH(B$5,ref_equipos!$A$2:$A$10,0))-B10)*INDEX(ref_equipos!$C$2:$C$10,MATCH(B$5,ref_equipos!$A$2:$A$10,0)) -> 0 | C19: =MAX(0,INDEX(ref_equipos!$H$2:$H$10,MATCH(C$5,ref_equipos!$A$2:$A$10,0))-C10)*INDEX(ref_equipos!$C$2:$C$10,MATCH(C$5,ref_equipos!$A$2:$A$10,0)) -> 0 | D19: =MAX(0,INDEX(ref_equipos!$H$2:$H$10,MATCH(D$5,ref_equipos!$A$2:$A$10,0))-D10)*INDEX(ref_equipos!$C$2:$C$10,MATCH(D$5,ref_equipos!$A$2:$A$10,0)) -> 0 | E19: Sesiones requeridas menos incluidas × precio por sesión
A20: Inversión total (USD) | B20: =SUM(B17:B19) -> 6900 | C20: =SUM(C17:C19) -> 6100 | D20: =SUM(D17:D19) -> 6900
A21: Recuperación (meses) | B21: =IF(B16<=0,"n/a",B20/B16) -> 10.147059 | C21: =IF(C16<=0,"n/a",C20/C16) -> 10.639535 | D21: =IF(D16<=0,"n/a",D20/D16) -> 25.555556 | E21: Inversión ÷ flujo
A22: Retorno a H meses | B22: =(B16*ref_parametros!$B$3-B20)/B20 -> 1.3652174 | C22: =(C16*ref_parametros!$B$3-C20)/C20 -> 1.2557377 | D22: =(D16*ref_parametros!$B$3-D20)/D20 -> -0.060869565 | E22: (Flujo × H − inversión) ÷ inversión
A23: Clínica viable (recuperación ≤ umbral) | B23: =IF(B16<=0,"No",IF(B20/B16<=ref_umbrales!$B$2,"Sí","No")) -> Sí | C23: =IF(C16<=0,"No",IF(C20/C16<=ref_umbrales!$B$2,"Sí","No")) -> Sí | D23: =IF(D16<=0,"No",IF(D20/D16<=ref_umbrales!$B$2,"Sí","No")) -> No | E23: Umbral: ref_umbrales (06, U-01)
A24: Tecnocare
A25: Ingreso total de la venta (USD) | B25: =B20 -> 6900 | C25: =C20 -> 6100 | D25: =D20 -> 6900
A26: Costo de adquisición del equipo (USD) | B26: =INDEX(ref_equipos!$E$2:$E$10,MATCH(B$5,ref_equipos!$A$2:$A$10,0)) -> 4200 | C26: =INDEX(ref_equipos!$E$2:$E$10,MATCH(C$5,ref_equipos!$A$2:$A$10,0)) -> 4200 | D26: =INDEX(ref_equipos!$E$2:$E$10,MATCH(D$5,ref_equipos!$A$2:$A$10,0)) -> 4200 | E26: ref_equipos (03)
A27: Costo de instalación (USD) | B27: =INDEX(ref_equipos!$F$2:$F$10,MATCH(B$5,ref_equipos!$A$2:$A$10,0)) -> 250 | C27: =INDEX(ref_equipos!$F$2:$F$10,MATCH(C$5,ref_equipos!$A$2:$A$10,0)) -> 250 | D27: =INDEX(ref_equipos!$F$2:$F$10,MATCH(D$5,ref_equipos!$A$2:$A$10,0)) -> 250 | E27: Se paga aunque la instalación vaya incluida
A28: Costo de capacitación (USD) | B28: =INDEX(ref_equipos!$H$2:$H$10,MATCH(B$5,ref_equipos!$A$2:$A$10,0))*INDEX(ref_equipos!$G$2:$G$10,MATCH(B$5,ref_equipos!$A$2:$A$10,0)) -> 120 | C28: =INDEX(ref_equipos!$H$2:$H$10,MATCH(C$5,ref_equipos!$A$2:$A$10,0))*INDEX(ref_equipos!$G$2:$G$10,MATCH(C$5,ref_equipos!$A$2:$A$10,0)) -> 120 | D28: =INDEX(ref_equipos!$H$2:$H$10,MATCH(D$5,ref_equipos!$A$2:$A$10,0))*INDEX(ref_equipos!$G$2:$G$10,MATCH(D$5,ref_equipos!$A$2:$A$10,0)) -> 120 | E28: Sesiones requeridas × costo por sesión
A29: Costo total (USD) | B29: =SUM(B26:B28) -> 4570 | C29: =SUM(C26:C28) -> 4570 | D29: =SUM(D26:D28) -> 4570
A30: Margen de Tecnocare (%) | B30: =(B25-B29)/B25 -> 0.33768116 | C30: =(C25-C29)/C25 -> 0.25081967 | D30: =(D25-D29)/D25 -> 0.33768116 | E30: (Ingreso − costo) ÷ ingreso
A31: Tecnocare viable (margen ≥ piso) | B31: =IF(B30>=ref_umbrales!$B$3,"Sí","No") -> Sí | C31: =IF(C30>=ref_umbrales!$B$3,"Sí","No") -> Sí | D31: =IF(D30>=ref_umbrales!$B$3,"Sí","No") -> Sí | E31: Piso: ref_umbrales (06, U-02)
A32: Precio mínimo del equipo para el piso (USD) | B32: =B29/(1-ref_umbrales!$B$3)-B18-B19 -> 5693.3333 | C32: =C29/(1-ref_umbrales!$B$3)-C18-C19 -> 6093.3333 | D32: =D29/(1-ref_umbrales!$B$3)-D18-D19 -> 5693.3333 | E32: Piso de la palanca 5
A33: Resultado de la zona de acuerdo | B33: =IF(AND(B23="Sí",B31="Sí"),"VIABLE (win-win)","NO VIABLE") -> VIABLE (win-win) | C33: =IF(AND(C23="Sí",C31="Sí"),"VIABLE (win-win)","NO VIABLE") -> VIABLE (win-win) | D33: =IF(AND(D23="Sí",D31="Sí"),"VIABLE (win-win)","NO VIABLE") -> NO VIABLE

Sheet ref_equipos
A1: product_id | B1: Instalación: precio de venta (USD) [02] | C1: Capacitación: precio por sesión (USD) [02] | D1: Insumo por sesión (USD) [03] | E1: Costo de adquisición (USD) [03] | F1: Costo de instalación (USD) [03] | G1: Costo de capacitación por sesión (USD) [03] | H1: Capacitación requerida (sesiones) [01]
A2: ozonette | B2: 400 | C2: 150 | D2: 15 | E2: 4200 | F2: 250 | G2: 60 | H2: 2
A3: ozonette_dent | B3: 400 | C3: 150 | D3: 15 | E3: 4400 | F3: 250 | G3: 60 | H3: 2
A4: ozonette_woman_care | B4: 400 | C4: 150 | D4: 15 | E4: 4400 | F4: 250 | G4: 60 | H4: 2
A5: ozonette_vet | B5: 400 | C5: 150 | D5: 12 | E5: 4000 | F5: 250 | G5: 60 | H5: 2
A6: ozonobaric_p | B6: 400 | C6: 150 | D6: 18 | E6: 4500 | F6: 250 | G6: 60 | H6: 2
A7: om_302_d | B7: 450 | C7: 180 | D7: 20 | E7: 4900 | F7: 300 | G7: 70 | H7: 2
A8: easyflow_r_60 | B8: 0 | C8: 0 | D8: 0 | E8: 15 | F8: 0 | G8: 0 | H8: 0
A9: easyflow_r_100 | B9: 0 | C9: 0 | D9: 0 | E9: 18 | F9: 0 | G9: 0 | H9: 0
A10: easyflow_r_300 | B10: 0 | C10: 0 | D10: 0 | E10: 24 | F10: 0 | G10: 0 | H10: 0

Sheet ref_parametros
A1: Parámetro | B1: Valor | C1: Unidad | D1: Fuente
A2: tipo_cambio | B2: 3.75 | C2: PEN por USD | D2: 04 · P-01
A3: horizonte_meses | B3: 24 | C3: meses | D3: 04 · P-03

Sheet ref_umbrales
A1: Parámetro | B1: Valor | C1: Unidad | D1: Fuente
A2: umbral_recuperacion_meses | B2: 12 | C2: meses | D2: 06 · U-01
A3: piso_margen | B3: 0.25 | C3: % | D3: 06 · U-02
